{"version":3,"kind":"Article","sha256":"e0439388e9d9b6957648530e27b7bb2bcbec61b6ddaa3584dabc78cde4a944c8","slug":"1-1","location":"/parent_1/part_1/1-1.md","dependencies":[],"frontmatter":{"title":"1-1","numbering":{"title":{"offset":2}},"exports":[{"format":"md","filename":"1-1.md","url":"/jb./build/1-1-4c99b4308f65ba2f1454b7c9e07ee05c.md"}]},"mdast":{"type":"root","children":[{"type":"block","children":[{"type":"paragraph","position":{"start":{"line":7,"column":1},"end":{"line":7,"column":1}},"children":[{"type":"text","value":"part-1-first-child","position":{"start":{"line":7,"column":1},"end":{"line":7,"column":1}},"key":"X5hhK58dLm"}],"key":"EDnxeAE3lO"}],"key":"xxkPWrbQW1"}],"key":"kHORYEwBgW"},"references":{"cite":{"order":[],"data":{}}},"footer":{"navigation":{"prev":{"title":"readme","url":"/","group":"readme"},"next":{"title":"1-2","url":"/1-2","group":"Part 1"}}},"domain":"http://localhost:3000"}