{"version":3,"kind":"Article","sha256":"e3b0c44298fc1c149afbf4c8996fb92427ae41e4649b934ca495991b7852b855","slug":"1-2-1","location":"/parent_2/part_1/1-2.md","dependencies":[],"frontmatter":{"numbering":{"title":{"offset":2}},"exports":[{"format":"md","filename":"1-2.md","url":"/jb./build/1-2-ee31ec42ad201935c477e44452f2cf77.md"}]},"mdast":{"type":"root","children":[],"key":"h1nJYHCvBK"},"references":{"cite":{"order":[],"data":{}}},"footer":{"navigation":{"prev":{"title":"1 1","url":"/1-1-1","group":"Part 1"},"next":{"title":"2 1","url":"/2-1-1","group":"Part 2"}}},"domain":"http://localhost:3000"}