{"version":3,"kind":"Article","sha256":"b28e32eb696a85696c25e65ed13f2b954953b61d6b333fdf380e9869cb8c0919","slug":"index2-1","location":"/mv/Kube/index2.md","dependencies":[],"frontmatter":{"title":"Clone GKE retail example","content_includes_title":false,"numbering":{"title":{"offset":2}},"exports":[{"format":"md","filename":"index2.md","url":"/jb./build/index2-fca92b7638e7dbf87df1b43938fc01a0.md"}]},"mdast":{"type":"root","children":[{"type":"block","children":[{"type":"code","lang":"bash","value":"git clone --depth 1 --branch v0 https://github.com/GoogleCloudPlatform/microservices-demo.git\ncd microservices-demo/","position":{"start":{"line":2,"column":1},"end":{"line":5,"column":1}},"key":"zof1Rh6QUc"},{"type":"list","ordered":false,"spread":false,"position":{"start":{"line":6,"column":1},"end":{"line":7,"column":1}},"children":[{"type":"listItem","spread":true,"position":{"start":{"line":6,"column":1},"end":{"line":6,"column":1}},"children":[{"type":"paragraph","children":[{"type":"text","value":"Export Google Cloud project and region and ensure the Google Kubernetes Engine API is enabled","position":{"start":{"line":6,"column":1},"end":{"line":6,"column":1}},"key":"A7Dvp3zQ3W"}],"key":"wEg9ZoMR4A"}],"key":"qgRzXBADfO"},{"type":"listItem","spread":true,"position":{"start":{"line":7,"column":1},"end":{"line":7,"column":1}},"children":[{"type":"paragraph","children":[{"type":"text","value":"Substitute <PROJECT_ID> with the ID of your Google Cloud project","position":{"start":{"line":7,"column":1},"end":{"line":7,"column":1}},"key":"S4ZfO74cf8"}],"key":"A7CETF7gkF"}],"key":"nhUk5g13w6"}],"key":"Lrq6UwKoBs"},{"type":"code","lang":"bash","value":"export PROJECT_ID=<PROJECT_ID>\nexport REGION=us-central1\ngcloud services enable container.googleapis.com \\\n  --project=${PROJECT_ID}","position":{"start":{"line":8,"column":1},"end":{"line":13,"column":1}},"key":"gXO1v8nnW6"},{"type":"list","ordered":false,"spread":false,"position":{"start":{"line":14,"column":1},"end":{"line":14,"column":1}},"children":[{"type":"listItem","spread":true,"position":{"start":{"line":14,"column":1},"end":{"line":14,"column":1}},"children":[{"type":"paragraph","children":[{"type":"text","value":"Create a GKE cluster and get the credentials for it","position":{"start":{"line":14,"column":1},"end":{"line":14,"column":1}},"key":"OgJ0k2YjO5"}],"key":"LYuoKNnydv"}],"key":"fDWWL3yM4O"}],"key":"J1XJ2g4B0n"},{"type":"code","lang":"bash","value":"gcloud container clusters create-auto online-boutique \\\n  --project=${PROJECT_ID} --region=${REGION}","position":{"start":{"line":15,"column":1},"end":{"line":18,"column":1}},"key":"RjOPcnQlGc"},{"type":"list","ordered":false,"spread":false,"position":{"start":{"line":19,"column":1},"end":{"line":19,"column":1}},"children":[{"type":"listItem","spread":true,"position":{"start":{"line":19,"column":1},"end":{"line":19,"column":1}},"children":[{"type":"paragraph","children":[{"type":"text","value":"Deploy App to cluster","position":{"start":{"line":19,"column":1},"end":{"line":19,"column":1}},"key":"xTRasF5LZn"}],"key":"dalHNysK0g"}],"key":"BQEVp7aI6Z"}],"key":"Hrv0PyHzdL"},{"type":"code","lang":"bash","value":"kubectl apply -f ./release/kubernetes-manifests.yaml","position":{"start":{"line":20,"column":1},"end":{"line":22,"column":1}},"key":"C6NulqFk4B"},{"type":"list","ordered":false,"spread":false,"position":{"start":{"line":23,"column":1},"end":{"line":24,"column":1}},"children":[{"type":"listItem","spread":true,"position":{"start":{"line":23,"column":1},"end":{"line":23,"column":1}},"children":[{"type":"paragraph","children":[{"type":"text","value":"Access the web frontend in a browser using the frontend’s external IP","position":{"start":{"line":23,"column":1},"end":{"line":23,"column":1}},"key":"Zm7hP6290C"}],"key":"eroeo94pQs"}],"key":"PZmZL0Q0cH"},{"type":"listItem","spread":true,"position":{"start":{"line":24,"column":1},"end":{"line":24,"column":1}},"children":[{"type":"paragraph","children":[{"type":"text","value":"Visit http://EXTERNAL_IP in a web browser to access your instance","position":{"start":{"line":24,"column":1},"end":{"line":24,"column":1}},"key":"uRjJ0HPJra"}],"key":"qYFtb6lXMq"}],"key":"YBw1zXoBBh"}],"key":"JXfnNCN2v2"},{"type":"code","lang":"bash","value":"kubectl get service frontend-external | awk '{print $4}'","position":{"start":{"line":25,"column":1},"end":{"line":27,"column":1}},"key":"CkJdJmK88k"},{"type":"list","ordered":false,"spread":false,"position":{"start":{"line":28,"column":1},"end":{"line":28,"column":1}},"children":[{"type":"listItem","spread":true,"position":{"start":{"line":28,"column":1},"end":{"line":28,"column":1}},"children":[{"type":"paragraph","children":[{"type":"text","value":"Delete cluster when finished","position":{"start":{"line":28,"column":1},"end":{"line":28,"column":1}},"key":"wDsnRaUEEr"}],"key":"HaI6gjpH9V"}],"key":"KdhFUyvzVK"}],"key":"Z73qHTjO2n"},{"type":"code","lang":"bash","value":"gcloud container clusters delete online-boutique \\\n  --project=${PROJECT_ID} --region=${REGION}","position":{"start":{"line":29,"column":1},"end":{"line":32,"column":1}},"key":"oZIUN02KO7"},{"type":"heading","depth":2,"position":{"start":{"line":33,"column":1},"end":{"line":33,"column":1}},"children":[{"type":"text","value":"Addition deployment options","position":{"start":{"line":33,"column":1},"end":{"line":33,"column":1}},"key":"nBUTp3wEMv"}],"identifier":"addition-deployment-options","label":"Addition deployment options","html_id":"addition-deployment-options","implicit":true,"key":"woaUPeXMXn"},{"type":"list","ordered":false,"spread":false,"position":{"start":{"line":34,"column":1},"end":{"line":40,"column":1}},"children":[{"type":"listItem","spread":true,"position":{"start":{"line":34,"column":1},"end":{"line":34,"column":1}},"children":[{"type":"paragraph","children":[{"type":"link","url":"https://github.com/GoogleCloudPlatform/microservices-demo/blob/main/terraform","position":{"start":{"line":34,"column":1},"end":{"line":34,"column":1}},"children":[{"type":"text","value":"Terraform","position":{"start":{"line":34,"column":1},"end":{"line":34,"column":1}},"key":"O835xDB5Sh"}],"urlSource":"https://github.com/GoogleCloudPlatform/microservices-demo/blob/main/terraform","data":{"kind":"file","org":"GoogleCloudPlatform","repo":"microservices-demo","reference":"main","file":"terraform","raw":"https://raw.githubusercontent.com/GoogleCloudPlatform/microservices-demo/main/terraform"},"internal":false,"protocol":"github","key":"BrZjJkXoPm"}],"key":"rUX6DXO1gG"}],"key":"rvWajCn4aP"},{"type":"listItem","spread":true,"position":{"start":{"line":35,"column":1},"end":{"line":35,"column":1}},"children":[{"type":"paragraph","children":[{"type":"link","url":"https://github.com/GoogleCloudPlatform/microservices-demo/blob/main/kustomize/components/service-mesh-istio/README.md","position":{"start":{"line":35,"column":1},"end":{"line":35,"column":1}},"children":[{"type":"text","value":"Istio/Cloud","position":{"start":{"line":35,"column":1},"end":{"line":35,"column":1}},"key":"uU8ddKeXRJ"}],"urlSource":"https://github.com/GoogleCloudPlatform/microservices-demo/blob/main/kustomize/components/service-mesh-istio/README.md","data":{"kind":"file","org":"GoogleCloudPlatform","repo":"microservices-demo","reference":"main","file":"kustomize/components/service-mesh-istio/README.md","raw":"https://raw.githubusercontent.com/GoogleCloudPlatform/microservices-demo/main/kustomize/components/service-mesh-istio/README.md"},"internal":false,"protocol":"github","key":"n6QsrzcFGJ"},{"type":"text","value":" Service Mesh","position":{"start":{"line":35,"column":1},"end":{"line":35,"column":1}},"key":"sZNC67Vm1r"}],"key":"XBJdj0kBYP"}],"key":"kcCyzHyBtc"},{"type":"listItem","spread":true,"position":{"start":{"line":36,"column":1},"end":{"line":36,"column":1}},"children":[{"type":"paragraph","children":[{"type":"link","url":"https://github.com/GoogleCloudPlatform/microservices-demo/blob/main/docs/development-guide.md","position":{"start":{"line":36,"column":1},"end":{"line":36,"column":1}},"children":[{"type":"text","value":"Non-GKE","position":{"start":{"line":36,"column":1},"end":{"line":36,"column":1}},"key":"AZzccqkLN9"}],"urlSource":"https://github.com/GoogleCloudPlatform/microservices-demo/blob/main/docs/development-guide.md","data":{"kind":"file","org":"GoogleCloudPlatform","repo":"microservices-demo","reference":"main","file":"docs/development-guide.md","raw":"https://raw.githubusercontent.com/GoogleCloudPlatform/microservices-demo/main/docs/development-guide.md"},"internal":false,"protocol":"github","key":"VE87cEfWOk"},{"type":"text","value":" (Minikube, Kind)","position":{"start":{"line":36,"column":1},"end":{"line":36,"column":1}},"key":"dVrrZuIvNK"}],"key":"IOKOTGmRVX"}],"key":"aIqNpi5fAh"},{"type":"listItem","spread":true,"position":{"start":{"line":37,"column":1},"end":{"line":37,"column":1}},"children":[{"type":"paragraph","children":[{"type":"link","url":"https://github.com/GoogleCloudPlatform/microservices-demo/blob/main/kustomize/components/shopping-assistant/README.md","position":{"start":{"line":37,"column":1},"end":{"line":37,"column":1}},"children":[{"type":"text","value":"AI","position":{"start":{"line":37,"column":1},"end":{"line":37,"column":1}},"key":"ZYi6DeFBVz"}],"urlSource":"https://github.com/GoogleCloudPlatform/microservices-demo/blob/main/kustomize/components/shopping-assistant/README.md","data":{"kind":"file","org":"GoogleCloudPlatform","repo":"microservices-demo","reference":"main","file":"kustomize/components/shopping-assistant/README.md","raw":"https://raw.githubusercontent.com/GoogleCloudPlatform/microservices-demo/main/kustomize/components/shopping-assistant/README.md"},"internal":false,"protocol":"github","key":"kdn5eT3vMF"},{"type":"text","value":" assistant using Gemini","position":{"start":{"line":37,"column":1},"end":{"line":37,"column":1}},"key":"P4Fj0NXB72"}],"key":"Z2EPA9HHA3"}],"key":"Uy3i7fvGHU"},{"type":"listItem","spread":true,"position":{"start":{"line":38,"column":1},"end":{"line":40,"column":1}},"children":[{"type":"paragraph","children":[{"type":"link","url":"https://github.com/GoogleCloudPlatform/microservices-demo/tree/main/kustomize","position":{"start":{"line":38,"column":1},"end":{"line":38,"column":1}},"children":[{"type":"text","value":"/kustomize","position":{"start":{"line":38,"column":1},"end":{"line":38,"column":1}},"key":"NAwCB0eW3e"}],"urlSource":"https://github.com/GoogleCloudPlatform/microservices-demo/tree/main/kustomize","error":true,"key":"fyrgo74SvZ"},{"type":"text","value":" directory contains instructions for customizing the deployment of Online Boutique with other variations","position":{"start":{"line":38,"column":1},"end":{"line":38,"column":1}},"key":"YwrVqZHBgm"}],"key":"w9Mba3IcNM"}],"key":"qs2B9rmDKf"}],"key":"M4dTeRjhab"}],"key":"jGYSZZPH9w"}],"key":"QKlXg8K2ty"},"references":{"cite":{"order":[],"data":{}}},"footer":{"navigation":{"prev":{"title":"KUBERNETES","url":"/index-3","group":"Kube"}}},"domain":"http://localhost:3000"}