{"version":3,"kind":"Article","sha256":"d43f05554a8ff69d2d36616ce238c11d5e7a6e69b3bfa13c847ad2483ea715c3","slug":"readme-39","location":"/mv/pages/legacy/site-old/temp/Globe/Sat/LEO/README.md","dependencies":[],"frontmatter":{"title":"LEO (Low Earth Orbit)","content_includes_title":false,"numbering":{"title":{"offset":5}},"exports":[{"format":"md","filename":"README.md","url":"/jb./build/README-2f89e9187c644647d06f6dc6f3631400.md"}]},"mdast":{"type":"root","children":[{"type":"block","children":[{"type":"paragraph","position":{"start":{"line":3,"column":1},"end":{"line":3,"column":1}},"children":[{"type":"text","value":"This directory contains data and resources related to low earth orbit satellites.","position":{"start":{"line":3,"column":1},"end":{"line":3,"column":1}},"key":"T43a3zE5BC"}],"key":"uYjJVFBhVH"},{"type":"paragraph","position":{"start":{"line":5,"column":1},"end":{"line":5,"column":1}},"children":[{"type":"text","value":"LEO satellites orbit close to Earth and are used for Earth observation, communications, and scientific missions.","position":{"start":{"line":5,"column":1},"end":{"line":5,"column":1}},"key":"QJ6FNz81oh"}],"key":"zCEnHUxMt7"}],"key":"XBdm6HmNJ6"}],"key":"yJXwpLFj2u"},"references":{"cite":{"order":[],"data":{}}},"footer":{"navigation":{"prev":{"title":"Cubesat","url":"/cubesat","group":"Temp"},"next":{"title":"MEO (Medium Earth Orbit)","url":"/readme-40","group":"Temp"}}},"domain":"http://localhost:3000"}